[
    {
        "name": "Tekton",
        "route": "tekton-dashboard",
        "description": "Manage your pipelines",
        "actionText": "Manage Pipelines",
        "https": true
    },
    {
        "name": "Application Navigator",
        "route": "kappnav-ui-service",
        "description": "Manage your applications using Application Navigator",
        "actionText": "Manage Applications",
        "https": true
    },
    {
        "name": "Red Hat CodeReady Workspaces",
        "route": "codeready",
        "description": "Red Hat CodeReady Workspaces provides a consistent, secure, and zero-configuration development environment.",
        "actionText": "Go to CodeReady",
        "https": true
    }
]